hbasethrift3/__init__.py
hbasethrift3/hbasethrift3.py
hbasethrift3-0.0.2.dist-info/LICENSE
hbasethrift3-0.0.2.dist-info/METADATA
hbasethrift3-0.0.2.dist-info/WHEEL
hbasethrift3-0.0.2.dist-info/top_level.txt
hbasethrift3-0.0.2.dist-info/RECORD
