Metadata-Version: 2.1
Name: hbasethrift3
Version: 0.0.2
Summary: hbasethrift3
Home-page: https://github.com/shawjan/hbasethrift3
Author: dfore
Author-email: darrenfore@gmail.com
License: UNKNOWN
Project-URL: Bug Tracker, https://github.com/shawjan/hbasethrift3/issues
Platform: UNKNOWN
Classifier: Programming Language :: Python :: 3
Classifier: License :: OSI Approved :: MIT License
Classifier: Operating System :: OS Independent
Requires-Python: >=3.5
License-File: LICENSE
